Metadata-Version: 2.1
Name: arnold-house-price-regression-model
Version: 0.0.5
Summary: Example regression model package by Arnold Ighiwiyisi
Home-page: https://github.com/Arnold-git/MLOp/tree/main/deploying-model-as-a-package
Author: ArnoldIG
Author-email: arnoldighiwiyisi@gmail.com
License: BSD-3
Platform: UNKNOWN
Classifier: License :: OSI Approved :: MIT License
Classifier: Programming Language :: Python
Classifier: Programming Language :: Python :: 3
Classifier: Programming Language :: Python :: 3.6
Classifier: Programming Language :: Python :: 3.7
Classifier: Programming Language :: Python :: 3.8
Classifier: Programming Language :: Python :: 3.9
Classifier: Programming Language :: Python :: Implementation :: CPython
Classifier: Programming Language :: Python :: Implementation :: PyPy
Requires-Python: >=3.6.0
Requires-Dist: feature-engine (<1.1.0,>=1.0.2)
Requires-Dist: joblib (==1.0.1)
Requires-Dist: numpy (<1.21.0,>=1.20.0)
Requires-Dist: pandas (<1.4.0,>==1.3.5)
Requires-Dist: pydantic (<1.9.0,>=1.8.1)
Requires-Dist: ruamel.yaml (==0.16.12)
Requires-Dist: scikit-learn (<0.25.0,>=0.24.0)
Requires-Dist: strictyaml (<1.4.0,>=1.3.2)
